{
  "updatedAt": "2026-03-07T09:59:43.959Z",
  "events": [
    {
      "title": "Lørdagskafé",
      "description": "Lørdag 07.03 kl.12.00 Lørdagskafé Kefas",
      "category": "mat-og-drikke",
      "dateTime": "2026-03-07T12:00:00",
      "location": "Brønnøy kirke",
      "url": "https://www.bronnoy.kirken.no/Kalender",
      "collectedAt": "2026-03-07T09:59:29.442Z",
      "id": "Brønnøy-kirke-2026-03-07T11:00:00.000Z"
    },
    {
      "id": "1160832496007102",
      "title": "Biff lørdag 🥩🥩🥩",
      "description": "Denne lørdagen fyrer vi opp grillen og serverer saftig, marmorert ytrefilet av storfe - perfekt grillet og full av smak. \n220 g biffen serveres med brokkolini og syltet løk, sammen med et utvalg av sauser og poteter som passer til enhver smak.\n\n🍴Tilbehør: grønn peppersaus, rødvinsaus, hollandaise eller chimichurri.\n🍠Poteter: røsti, pommes frites eller luftig potetpuré.\n\n💵Pris: 465,-\nTilgjengelig fra kl. 15:00 til 22:00, eller så lenge beholdningen rekker.\n‼️Drop in!!",
      "category": "mat-og-drikke",
      "dateTime": "2026-03-07T14:00:00.000Z",
      "location": "Storgata 68, 8900 Brønnøysund, Norway",
      "url": "https://www.facebook.com/events/1160832496007102/",
      "collectedAt": "2026-03-07T09:11:44.694Z"
    },
    {
      "id": "2124299738364179",
      "title": "Kred's Musikkbingo",
      "description": "Vi er på senvinteren og venter fortsatt på våren. Hva passer bedre nå på kaldeste vinteren enn å ta turen innom og være med på Kred's Musikk-Bingo! Temaene er ikke bestemt enda, men det blir gøy uansett.\n\nVår bingovert tar dere med til musikkens historie. Vi spiller musikk, du finner ut sangen og ser om den er på bingobrettet. Vanskeligere er det ikke! Alle tidligere deltakere synes dette er kjempegøy.\n\nVi spiller to runder med bingo. Det koster kr. 50,- for bingobrett, og du betaler bare en gang for hele kvelden.\n\nVi har 18-årsgrense.",
      "category": "quiz",
      "dateTime": "2026-03-07T20:00:00.000Z",
      "location": "Kred",
      "url": "https://www.facebook.com/events/2124299738364179/",
      "collectedAt": "2026-03-07T09:11:41.557Z"
    },
    {
      "title": "Gudstjeneste",
      "description": "Søndag 08.03 kl.18.00 Gudstjeneste Gudstjeneste - Brønnøy kirke",
      "category": "tro-og-livssyn",
      "dateTime": "2026-03-08T18:00:00",
      "location": "Brønnøy kirke",
      "url": "https://www.bronnoy.kirken.no/Kalender",
      "collectedAt": "2026-03-07T09:59:29.442Z",
      "id": "Brønnøy-kirke-2026-03-08T17:00:00.000Z"
    },
    {
      "title": "Barseltreff på bibliotek",
      "description": "Barseltreff på bibliotek",
      "category": "barn-og-ungdom",
      "dateTime": "2026-03-10T11:00:00",
      "location": "Brønnøy bibliotek",
      "url": "https://bronnoybibliotek.no/arrangementer#/",
      "collectedAt": "2026-03-07T09:58:47.703Z",
      "id": "Brønnøy-bibliotek-2026-03-10T10:00:00.000Z"
    },
    {
      "title": "Åpent folkemøte om områderegulering for Brønnøy Kalk",
      "description": "Helgeland Museum i Velfjord",
      "category": "kommunalt",
      "dateTime": "2026-03-10T18:00:00",
      "location": "Brønnøy kommune",
      "url": "https://www.bronnoy.kommune.no/",
      "collectedAt": "2026-03-07T09:58:08.383Z",
      "id": "Brønnøy-kommune-2026-03-10T17:00:00.000Z"
    },
    {
      "title": "Operasjon Bever",
      "description": "Operasjon Bever",
      "category": "kino",
      "dateTime": "2026-03-10T18:00:00",
      "location": "Brønnøy kino",
      "url": "https://www.bronnoy.kommune.no/kino/",
      "collectedAt": "2026-03-07T09:58:15.856Z",
      "id": "Brønnøy-kino-2026-03-10T17:00:00.000Z"
    },
    {
      "title": "Wuthering Heights",
      "description": "Wuthering Heights",
      "category": "kino",
      "dateTime": "2026-03-10T20:00:00",
      "location": "Brønnøy kino",
      "url": "https://www.bronnoy.kommune.no/kino/",
      "collectedAt": "2026-03-07T09:58:15.856Z",
      "id": "Brønnøy-kino-2026-03-10T19:00:00.000Z"
    },
    {
      "title": "Trille-Tralle-Treff (babysang)",
      "description": "Onsdag 11.03 kl.11.00 Trille-Tralle-Treff (babysang) Barn og unge - Kefas",
      "category": "barn-og-ungdom",
      "dateTime": "2026-03-11T11:00:00",
      "location": "Brønnøy kirke",
      "url": "https://www.bronnoy.kirken.no/Kalender",
      "collectedAt": "2026-03-07T09:59:29.442Z",
      "id": "Brønnøy-kirke-2026-03-11T10:00:00.000Z"
    },
    {
      "title": "Diktkveld med forfatter Ola-Jørn Tilrem",
      "description": "Diktkveld med forfatter Ola-Jørn Tilrem",
      "category": "kunst-og-kultur",
      "dateTime": "2026-03-11T17:00:00",
      "location": "Brønnøy bibliotek",
      "url": "https://www.facebook.com/events/1240506438009961/",
      "collectedAt": "2026-03-07T09:11:44.085Z"
    },
    {
      "title": "Diktkveld med forfatter Ola-Jørn Tilrem",
      "description": "Brønnøy bibliotek inviterer til diktkveld med forfatter Ola-Jørn Tilrem\n\nTid: Onsdag 11. mars kl. 18:00\nSted: Brønnøy bibliotek, Brønnøysund\n\nTilrem – pensjonert bonde og aktuell poet – kom i år ut med boka «Kastevind», ei diktsamling utgitt på eget forlag. Dikta, som ifølge han sjøl er skrevet til «vanlige folk», er fulle av lengsel, varme, livsvisdom og humor – og med kjærlighet til naturen og mennesker som rød tråd. \n\nDette blir ei lun og lærerik stund med forfatterens tekster og betraktninger rundt sitt eget liv og virke i fokus.\n\nVelkommen!",
      "category": "kunst-og-kultur",
      "dateTime": "2026-03-11T18:00:00",
      "location": "Brønnøy bibliotek",
      "url": "https://bronnoybibliotek.no/arrangementer#/",
      "collectedAt": "2026-03-07T09:58:47.703Z",
      "id": "Brønnøy-bibliotek-2026-03-11T17:00:00.000Z"
    },
    {
      "id": "4463441877217520",
      "title": "Onsdagsquiz på Den Andre Puben 😊",
      "description": "Litt av alt, gratis å delta og god stemning😁\nVinneren får velge neste ukes gjestekategori🥳",
      "category": "quiz",
      "dateTime": "2026-03-11T19:00:00.000Z",
      "location": "Den andre puben",
      "url": "https://www.facebook.com/events/4463441877217520/",
      "collectedAt": "2026-03-07T09:11:42.475Z"
    },
    {
      "title": "Hamnet",
      "description": "Hamnet",
      "category": "kino",
      "dateTime": "2026-03-11T20:00:00",
      "location": "Brønnøy kino",
      "url": "https://www.bronnoy.kommune.no/kino/",
      "collectedAt": "2026-03-07T09:58:15.856Z",
      "id": "Brønnøy-kino-2026-03-11T19:00:00.000Z"
    },
    {
      "id": "1613391163248701",
      "title": "Fornøyelsespark BVS for dreamskolen",
      "description": "For andre år på rad arrangerer Brønnøysund videregående skole fornøyelsespark i skolebygget. Fornøyelsesparken har som formål å samle inn penger til De Makalause som skal bygge skole for funksjonshemmede på Sri Lanka! I 2025 samlet vi inn 55 000 kr.😊\n\nTorsdag 12. mars vil skolen fylles med aktiviteter for både barn og voksne, unge og eldre.\n\nHer er noen smakebiter på moroa som venter under solidaritetsaksjonen:\n⭐ Salg av egenproduserte varer✨🛍️\n⭐ Quiz❓\n⭐ Rebusløype🧩\n⭐ Sveisesimulator👨‍🏭\n⭐ Familiebilde📸\n⭐ Mange ulike kafeer på skolen☕🍰\n⭐ Klovn som selger ballongdyr🤡\n⭐ Labyrint 🌀\n⭐ Lekerom 🧸🎨 \n⭐ Ansiktsmaling 🖌️\n⭐ Beautysalong\n⭐ VR-briller\n\nTilbudene er mange! 🎉\n\n🍽️ Middag kan kjøpes i skolens kantine.\n\n🎶 Det vil også være konserter av elever fra skolen.\n\n💖 Inntekten av kveldens solidaritetsaksjon går til Makalause Dream School på Sri Lanka 🌍❤️\n\nVelkommen og spre ordet utover i regionen til familie, naboer og bekjente 🗣️👨‍👩‍👧‍👦 Vi håper på å kunne fylle skolen med besøkende både for å vise frem den flotte skolen vår 🏫 og for å samle inn til skolens solidaritetsaksjon 💪.\n\n🎟️ Inngangspris:\n25,- for barn og 50,- for voksne.\nInngangsbilletten gir deg mulighet for å prøve en rekke ulike aktiviteter ved skolen 🤸‍♀️\n\nVelkommen! 🌟",
      "category": "barn-og-ungdom",
      "dateTime": "2026-03-12T14:00:00.000Z",
      "location": "Brønnøysund videregående skole",
      "url": "https://www.facebook.com/events/1613391163248701/",
      "collectedAt": "2026-03-07T09:11:45.327Z"
    },
    {
      "id": "26225559823797002",
      "title": "RETROCUP Turnering",
      "description": "Er du klar for den ultimate retro-opplevelsen? 🎮\n\nBli med på RETROCUP, en legendarisk CS 1.6 LAN-turnering i regi av IT-klassen for å markere årets Solidaritetsdag! Vi skrur tiden tilbake til da ferdigheter betydde alt и lagg var din største fiende.\n\nViktig informasjon:\n📍 Sted: A102-rommet, Brønnøysund videregående skole.\n📅 Dato: 12. mars 2026.\n🕒 Tid: 15:15 – 20:00.\n💰 Pris: 50 kr per person (250 kr per lag). Alle inntekter går uavkortet til Solidaritetsaksjonen.\n\nFormat:\n🏆 5 mot 5 (maks 8 lag).\n⚔️ BO1 (Best of 1) i innledende runder.\n🔥 BO3 (Best of 3) i den store finalen.\n\nHvorfor delta?\nDette er ikke bare en kamp om ære – det er en sjanse til å bidra til en god sak. Vi har satt opp et profesjonelt nettverk med utstyr fra Cisco og Netgate for å sikre 0 ms forsinkelse og en perfekt spillopplevelse.\n\n🎥 Live Streaming:\nHele turneringen vil bli streamet direkte på YouTube og Twitch via Yolobox.\n\nPåmelding:\nDet er førstemann til mølla!\n🔗 Meld på ditt lag her: https://forms.cloud.microsoft/e/puBtqCyBUV\n🔗 Solo-spiller? Registrer deg her: https://forms.cloud.microsoft/e/ckMQTykdT0\n\nMerk: Ved påmelding samтыkker du til at ditt spill-alias og bilde/video kan bli vist på vår livestream.\n\nVi ses på serveren! GG WP! 🤝🎮",
      "category": "annet",
      "dateTime": "2026-03-12T14:15:00.000Z",
      "location": "Brønnøysund videregående skole",
      "url": "https://www.facebook.com/events/26225559823797002/",
      "collectedAt": "2026-03-07T09:11:45.851Z"
    },
    {
      "id": "761700400299768",
      "title": "Misery // Forsamlingslokalet Brønnøysund, Brønnøysund",
      "description": "Isolert. Skadet. Alene, med sin aller største beundrer.\n\nEtt hus. To mennesker. Ingen vei ut.\nVinden river i veggene. Inne i senga ligger Paula, den berømte forfatteren. Slått ut etter en bilulykke.\nIsolert og alene. Uten kontakt med omverdenen. Uten at noen vet hvor hun er.\nAnnie, sykepleieren med det milde smilet og de varme hendene, fant henne i snøen og reddet livet hennes. Paulas største beundrer, som har slukt alt hun har skrevet. Gjentatte ganger.\nNå har hun Paula helt for seg selv.\nAnnie kaller det kjærlighet. Omsorg. Hengiven pleie tilbake til livet. Men Paula forstår etter hvert at noe er galt, veldig galt.\nHun skrev for et publikum. Nå skriver hun for én.\nUhyggen kryper under huden.\n\nPsykologisk thriller om besettelse og fangenskap, av William Goldman, basert på Stephen Kings internasjonale bestselger.\n\nNoen historier slipper deg ikke. De setter seg i kroppen og blir der lenge etter at scenelyset har sluknet. Misery er teater for deg som vil kjenne pulsen stige og mørket krype under huden. Dette blir et intenst teatermøte der du sitter tett på scenen og kjenner spenningen dirre i rommet.\n\nForestillingen passer for et ungt og voksent publikum fra 16 år og oppover.\n\nPremiere: 7. februar 2026 (Vinterlysfestivalen)\n\nAv: William Goldman\nBasert på romanen av: Stephen King\nRegissør: Hanne Brincker\nSkuespillere: Vera Holte, Elisabet Sevholt og Rune Løding Storsæther\n\nVarighet: 90 minutter, uten pause\nOBS: Begrenset antall plasser, alle billetter unummerert.\n\nPriser: Ordinær kr 315 / U 30 kr 180 / Grupper 4+ kr 260\n\nVelkommen til en grufull god opplevelse!",
      "category": "kunst-og-kultur",
      "dateTime": "2026-03-12T18:00:00.000Z",
      "location": "Forsamlingslokalet Brønnøysund",
      "url": "https://www.facebook.com/events/761700400299768/",
      "collectedAt": "2026-03-07T09:11:39.329Z"
    },
    {
      "title": "AllmenQuiz",
      "description": "Quiz på Kred er inne i sitt 17 år. Det startet som en ren musikk-quiz, men nå kjører vi allmenquiz med spørsmål om litt av hvert. Quizmaster er den samme, bare enda mer kritisk, satirisk, nerdete og sta enn før. Det blir 16 kvelder i denne vinter-/vårserien. Vi kårer et vinnerlag hver runde, samt trekker premier blant deltakerne. Det blir også kåret en sammenlagtvinner ved serieslutt. Dette laget vinner et gavekort for en større pengesum som kan brukes på Kred.",
      "category": "quiz",
      "dateTime": "2026-03-12T20:00:00",
      "location": "Kred",
      "url": "https://www.cafekred.no/arrangementer",
      "collectedAt": "2026-03-07T09:58:24.097Z",
      "id": "Kred-2026-03-12T19:00:00.000Z"
    },
    {
      "title": "Gudstjeneste",
      "description": "Søndag 15.03 kl.11.00 Gudstjeneste Gudstjeneste - Brønnøy kirke",
      "category": "tro-og-livssyn",
      "dateTime": "2026-03-15T11:00:00",
      "location": "Brønnøy kirke",
      "url": "https://www.bronnoy.kirken.no/Kalender",
      "collectedAt": "2026-03-07T09:59:29.442Z",
      "id": "Brønnøy-kirke-2026-03-15T10:00:00.000Z"
    },
    {
      "id": "2129729637781721",
      "title": "KURS Pilhjerte kr 950,- inkl materialer",
      "description": "Artig pilkurs med Klara Pil hvor vi lager de flotteste pilhjerter på en metallramme. Koselig å ha på veggen hele året og veldig dekorativt med lys i desember💚\nKaffe/te og kake inkl.\nPåmelding el spørsmål; \n Trine Laumann(Skreddervika gård) tlf 47 24 43 41",
      "category": "annet",
      "dateTime": "2026-03-17T09:00:00.000Z",
      "location": "Kefas, Dr.Møllersgata 2, 8900 Brønnøysund",
      "url": "https://www.facebook.com/events/2129729637781721/",
      "collectedAt": "2026-03-07T09:11:43.740Z"
    },
    {
      "title": "Barseltreff på bibliotek",
      "description": "Barseltreff på bibliotek",
      "category": "barn-og-ungdom",
      "dateTime": "2026-03-17T11:00:00",
      "location": "Brønnøy bibliotek",
      "url": "https://bronnoybibliotek.no/arrangementer#/",
      "collectedAt": "2026-03-07T09:58:47.703Z",
      "id": "Brønnøy-bibliotek-2026-03-17T10:00:00.000Z"
    },
    {
      "id": "1474715997583350",
      "title": "KURS Pilhjerte kr 950,- inkl. materialer",
      "description": "Artig Pilkurs med Klara pil hvor  vi lager de flotteste pilhjerter på metallramme. Koselig å ha på veggen hele året og veldig dekorativt med lys i desember 💚\nKaffe/te og kake inkl.\nPåmeldig og evt spørsmål; \nTrine Laumann(Skreddervika gård) tlf 47 24 43 41",
      "category": "kunst-og-kultur",
      "dateTime": "2026-03-17T16:00:00.000Z",
      "location": "Kefas, Dr.Møllers gt 2, 8900 Brønnøysund",
      "url": "https://www.facebook.com/events/1474715997583350/",
      "collectedAt": "2026-03-07T09:11:44.303Z"
    },
    {
      "id": "1290807762936378",
      "title": "Gründerkveld på MEIR",
      "description": "Velkommen til en lavterskel møteplass på Gründerhuset ME!R for du som har starta, eller er interessert i å starte, virksomhet på Sør-Helgeland. \n\nDet blir gratis pizza, nettverksbygging & inspirasjonsprat med gründere.\n\nVil du ha pizza? Husk å melde deg på: https://forms.office.com/e/hN0LgaznsC\n\nArrangementet arrangeres av de gode hjelperne (Kunnskapsparken Helgeland, Sentrum Næringshage og Kystinkubatoren) som er finansiert av Nordland Fylkeskommune.  Vertsskap er Brønnøy Næringsforum sitt nye lokale. ",
      "category": "næringsliv",
      "dateTime": "2026-03-17T18:00:00.000Z",
      "location": "Storgata 51, 8900 Brønnøysund, Norge",
      "url": "https://www.facebook.com/events/1290807762936378/",
      "collectedAt": "2026-03-07T09:11:43.047Z"
    },
    {
      "title": "Trille-Tralle-Treff (babysang)",
      "description": "Onsdag 18.03 kl.11.00 Trille-Tralle-Treff (babysang) Barn og unge - Kefas",
      "category": "barn-og-ungdom",
      "dateTime": "2026-03-18T11:00:00",
      "location": "Brønnøy kirke",
      "url": "https://www.bronnoy.kirken.no/Kalender",
      "collectedAt": "2026-03-07T09:59:29.442Z",
      "id": "Brønnøy-kirke-2026-03-18T10:00:00.000Z"
    },
    {
      "id": "1400890462144393",
      "title": "SkatteFUNN-seminar i Brønnøy",
      "description": "Jobber din bedrift med å utvikle nye varer og tjenester eller en ny produksjonsprosess? Gjennom SkatteFUNN kan du få dekket inntil 19 % av utviklingsutgiftene dine. \n\nI samarbeid mellom Kunnskapsparken Helgeland, Sentrum Næringshage, Kystinkubatoren og Forskningsrådet arrangeres seminar med informasjon om SkatteFUNN ordningen.  \n  \nSkatteFUNN er en enkel og effektiv skattefradragsordning. I seminaret får du informasjon om hvilke typer forsknings- og utviklingsaktiviteter ordningen omfatter. Du får også tips og råd i forhold til selve søknadsprosessen, hvilke kriterier som vurderes, hvem som kan hjelpe deg, og hva du bør passe på å tydeliggjøre når du beskriver prosjektet ditt.  \n\nDette er for bedrifter, samarbeidspartnere og alle som planlegger kunnskapsarbeid, eller forskningsprosjekter i forbindelse med utvikling av nye varer, tjenester eller produksjonsprosesser.\n\nSentrale stikkord for seminaret her:\n•\tHva er SkatteFUNN \n•\tHva er forsking og utvikling, og hvilke prosjekter er det som faller utenfor \n•\tGod prosjektstruktur \n•\tProsjekteksempler \n•\tMuligheter og begrensninger \n•\tEvt. behov for oppfølging \n\nDet er flott dersom deltagerne har med egne ideer eller case som de evt. ønsker å diskutere i plenum eller 1:1 i etterkant av seminaret. \n",
      "category": "næringsliv",
      "dateTime": "2026-03-18T11:00:00.000Z",
      "location": "Storgata 51, 8900 Brønnøysund, Norge",
      "url": "https://www.facebook.com/events/1400890462144393/",
      "collectedAt": "2026-03-07T09:11:43.343Z"
    },
    {
      "title": "Gudstjeneste",
      "description": "Torsdag 19.03 kl.11.30 Gudstjeneste Gudstjeneste - Sykehjemmets kapell",
      "category": "tro-og-livssyn",
      "dateTime": "2026-03-19T11:30:00",
      "location": "Brønnøy kirke",
      "url": "https://www.bronnoy.kirken.no/Kalender",
      "collectedAt": "2026-03-07T09:59:29.442Z",
      "id": "Brønnøy-kirke-2026-03-19T10:30:00.000Z"
    },
    {
      "title": "Formiddagsfilmen: LOOP (2005)",
      "description": "Formiddagsfilmen: LOOP (2005)\n\nBrønnøy bibliotek inviterer til filmvisning på formiddagen torsdag 19. mars kl. 13:00.\n\nVi viser den norske dokumentarfilmen LOOP fra 2005.\n\nFilmen handler om forskjellige mennesker som lever livet litt utenfor normen. Vi følger bl.a. filosofen Arne Næss, en skogvokter i Østfold og to fiskere på ferd i en nordlandsbåt. \n\nFormiddagsfilmen er et lavterskeltilbud som er åpent for alle som ønsker seg en aktivitet på dagtid eller et samlingspunkt. Kom som du er og gå når du vil!\n\nFilmen varer i 1 time og 17 minutter.",
      "category": "kino",
      "dateTime": "2026-03-19T13:00:00",
      "location": "Brønnøy bibliotek",
      "url": "https://bronnoybibliotek.no/arrangementer#/",
      "collectedAt": "2026-03-07T09:58:47.703Z",
      "id": "Brønnøy-bibliotek-2026-03-19T12:00:00.000Z"
    },
    {
      "id": "1592827455088754",
      "title": "Mat og vinkveld med Erik Strugstad",
      "description": "Kred arrangerer en spennende mat og vinkveld med Erik Strugstad. Kom å lær litt om vin, samtidig som du får deg et godt måltid. Ingen forkunnskaper om vin er nødvendig, her skal vi bare nyte og kose oss. \n\nDenne kvelden serverer vi en 4-retters meny med 5 viner til. \nAperitif - Krostini med røkelakskrem\nForrett - Husets fiskesuppe med grissini\nHovedrett - Sliders, to forskjellige smaker akkompagnert av baconkroketter. \nDessert: Sjokoladefondant med bringebærsorbet. \n\nErik er Sommelier og innehaver av Introductory Sommelier-sertifikat fra Court of Master Sommeliers.\nTidligere Head Sommelier på Britannia, vinansvarlig ved flere av Trondheims beste restauranter, tidligere Norges yngste vinkelner, første vinner av Jeunes Sommeliers Norge. Han drev også tidligere Levanch, Norges største private vinklubb. \n\nPris per pers 995kr\n(4-retter og 5 viner er inkludert). \n\nPåmelding til post@cafekred.no eller 91848747\n",
      "category": "mat-og-drikke",
      "dateTime": "2026-03-20T18:00:00.000Z",
      "location": "Kred",
      "url": "https://www.facebook.com/events/1592827455088754/",
      "collectedAt": "2026-03-07T09:11:40.671Z"
    },
    {
      "id": "803770719136708",
      "title": "Distriktsmesterskap på Trekkspill 2026",
      "description": "Det nærmer seg distriktsmesterskap på trekkspill!\nVi jobber nå med å få til arrangementet i Brønnøysund helga 20.–22. mars 2026.\n\nHer på siden vil vi fortløpende legge ut informasjon om arrangementet.\n\nHjelp oss å spre budskapet!\nInviter gjerne trekkspillvenner og andre interesserte til å bli med på ei trivelig helg i Brønnøysund.\n\nInvitasjoner med mer informasjon – blant annet om overnatting og rabattkode – sendes ut på e-post til dem vi har e-postadresse til i løpet av kort tid. Samme informasjon vil også bli lagt ut her på siden.\n\nVelkommen til ei hyggelig og musikalsk helg i Brønnøysund!\n\nNB: Det tas forbehold om tilstrekkelig deltakelse for gjennomføring av arrangementet.",
      "category": "musikk",
      "dateTime": "2026-03-20T19:00:00.000Z",
      "location": "Brønnøysund samfunnshus",
      "url": "https://www.facebook.com/events/803770719136708/",
      "collectedAt": "2026-03-07T09:11:41.893Z"
    },
    {
      "title": "Gudstjeneste",
      "description": "Søndag 22.03 kl.11.00 Gudstjeneste Gudstjeneste - Brønnøy kirke",
      "category": "tro-og-livssyn",
      "dateTime": "2026-03-22T11:00:00",
      "location": "Brønnøy kirke",
      "url": "https://www.bronnoy.kirken.no/Kalender",
      "collectedAt": "2026-03-07T09:59:29.442Z",
      "id": "Brønnøy-kirke-2026-03-22T10:00:00.000Z"
    },
    {
      "title": "Barseltreff på bibliotek",
      "description": "Barseltreff på bibliotek",
      "category": "barn-og-ungdom",
      "dateTime": "2026-03-24T11:00:00",
      "location": "Brønnøy bibliotek",
      "url": "https://bronnoybibliotek.no/arrangementer#/",
      "collectedAt": "2026-03-07T09:58:47.703Z",
      "id": "Brønnøy-bibliotek-2026-03-24T10:00:00.000Z"
    },
    {
      "title": "Trille-Tralle-Treff (babysang)",
      "description": "Onsdag 25.03 kl.11.00 Trille-Tralle-Treff (babysang) Barn og unge - Kefas",
      "category": "barn-og-ungdom",
      "dateTime": "2026-03-25T11:00:00",
      "location": "Brønnøy kirke",
      "url": "https://www.bronnoy.kirken.no/Kalender",
      "collectedAt": "2026-03-07T09:59:29.442Z",
      "id": "Brønnøy-kirke-2026-03-25T10:00:00.000Z"
    },
    {
      "id": "866619559201849",
      "title": "Energetic Lydbad/Gongbad Opplevelse Brønnøysund",
      "description": "Velkommen til Lyd og Gongbad i Brønnøy Frivilligsentral, 25 Mars kl 18.\nHer kan du få muligheten til å oppleve Gongenes og frekvensenses dype hvile.\nHar og med en ny Merkaba Gong :-)\nLyd er energi og skaper frekvenser som påvirker oss både fysisk og på sjelsnivå. Gongbadet kan bidra til å frigjøre stress og blokkeringer i både kropp og sinn, rense og balansere energisenterene og bygge opp ditt energifeltet.\nHvilken lyd eller vibrasjon som er den beste for deg, avhenger av hva du trenger for stunden, og med mange gonger blir det bra spekter av frekvenser.\nLever man et rolig og avslappet liv, vil kanskje et Gong bad med mer «trøkk» gi mest påfyll. Lever man med stadig stress og jag, så vil kanskje de dypere og rolige tonene være dem som gir mest påfyll og bygger opp energifeltet ditt.\nUansett hva du måtte behøve, det som er sikkert er at du vil gå hjem annerledes enn når du kom!\nOpplev de dype frigjørende, healende tonene og vibrasjonene som Gongene og Syngebollen kan gi.\nDet blir først en kort oppvarming med Gong, med en kort deling om erfaringen, fær vi avslutter med ett lengre Lydbad. Har vi tid på slutten, er det åpen for deling.\nTA med tykt liggeunderlag, eller en god stol, for under Gongbadet er det anbefalt å ligge ned, eller sitte behagelig slik at kroppen kan slappe helt av. Tanken er å la seg flyte med i elven av lyder og vibrasjoner og la seg bade i dette vibrasjonsfeltet av lyder og frekvenser som trigger kroppens evne til healing og oppvåkning.\nInge Joar Holsen har siden 2006 drevet med Awareness meditasjon, samt utført Healinger og gitt Gongbad rundt om i Norge og verden. Han studerer og dypere Human Design programmet, og kan dele litt om det mellom Gongrundene\n\nPris: kr 550. \n\nTa med pledd, tykk matte, stol, så du kan sitte/ligge meget behagelig.\nFor mer info kontakt:\nPer Alfred Halsaunet eller\nInge Joar Holsen via E-post ijh@energeticrelease.com.",
      "category": "annet",
      "dateTime": "2026-03-25T17:00:00.000Z",
      "location": "Brønnøy Frivilligsentral",
      "url": "https://www.facebook.com/events/866619559201849/",
      "collectedAt": "2026-03-07T09:11:39.053Z"
    },
    {
      "id": "1535081147792962",
      "title": "Christer Torjussen: Stand Up Spesial",
      "description": "Christer Torjussen: Stand Up Spesial\n\nVelkommen til en kveld med en av landets mest rutinerte komikere! Christer er en veteran i humorfaget med over 25 års fartstid på standupscenen og har treffsikker humor, høy gjenkjennelsesfaktor og en god porsjon selvironi som varemerke. Som en anmelder skriver: Torjussen er den rene mitraljøsen, og poengene renner ut i raskt tempo!\n\nI tillegg til å være fast inventar på Latter i Oslo har han turnert konstant siden debuten i 1999 og har tre soloshow på merittlisten, blant annet “Drittpappa” som fikk strålende mottagelse og flere seksere på terningen, etterfulgt av «Idiot» og «MidtlivsChrister». Han gikk også viralt på nettet under pandemien med «Tid for Bok» hvor han byttet ut ord fra fagbøker og fikk etterhvert millioner med visninger. \n\nTorjussen har også mottatt Komiprisen for beste standup, samt den prestisjetunge Stå Opp-prisen.",
      "category": "kunst-og-kultur",
      "dateTime": "2026-03-27T20:00:00.000Z",
      "location": "Kred",
      "url": "https://www.facebook.com/events/1535081147792962/",
      "collectedAt": "2026-03-07T09:11:40.401Z"
    },
    {
      "title": "Barseltreff på bibliotek",
      "description": "Barseltreff på bibliotek",
      "category": "barn-og-ungdom",
      "dateTime": "2026-03-31T11:00:00",
      "location": "Brønnøy bibliotek",
      "url": "https://bronnoybibliotek.no/arrangementer#/",
      "collectedAt": "2026-03-07T09:58:47.703Z",
      "id": "Brønnøy-bibliotek-2026-03-31T09:00:00.000Z"
    },
    {
      "title": "Trille-Tralle-Treff (babysang)",
      "description": "Onsdag 01.04 kl.11.00 Trille-Tralle-Treff (babysang) Barn og unge - Kefas",
      "category": "barn-og-ungdom",
      "dateTime": "2026-04-01T11:00:00",
      "location": "Brønnøy kirke",
      "url": "https://www.bronnoy.kirken.no/Kalender",
      "collectedAt": "2026-03-07T09:59:29.442Z",
      "id": "Brønnøy-kirke-2026-04-01T09:00:00.000Z"
    },
    {
      "title": "Barseltreff på bibliotek",
      "description": "Barseltreff på bibliotek",
      "category": "barn-og-ungdom",
      "dateTime": "2026-04-07T11:00:00",
      "location": "Brønnøy bibliotek",
      "url": "https://bronnoybibliotek.no/arrangementer#/",
      "collectedAt": "2026-03-07T09:58:47.703Z",
      "id": "Brønnøy-bibliotek-2026-04-07T09:00:00.000Z"
    },
    {
      "title": "Trille-Tralle-Treff (babysang)",
      "description": "Onsdag 08.04 kl.11.00 Trille-Tralle-Treff (babysang) Barn og unge - Kefas",
      "category": "barn-og-ungdom",
      "dateTime": "2026-04-08T11:00:00",
      "location": "Brønnøy kirke",
      "url": "https://www.bronnoy.kirken.no/Kalender",
      "collectedAt": "2026-03-07T09:59:29.442Z",
      "id": "Brønnøy-kirke-2026-04-08T09:00:00.000Z"
    },
    {
      "title": "Lørdagskafé",
      "description": "Lørdag 11.04 kl.12.00 Lørdagskafé Kefas",
      "category": "mat-og-drikke",
      "dateTime": "2026-04-11T12:00:00",
      "location": "Brønnøy kirke",
      "url": "https://www.bronnoy.kirken.no/Kalender",
      "collectedAt": "2026-03-07T09:59:29.442Z",
      "id": "Brønnøy-kirke-2026-04-11T10:00:00.000Z"
    },
    {
      "id": "1214003247388441",
      "title": "Konsert med JONAS KNUTSSON og OBROY - distriktsmusikerne i Brønnøy",
      "description": "I to uker i april kommer den svenske saksofonisten Jonas Knutsson til Brønnøysund for å spille med lokale musikere, og til denne konserten er det med OBROY.\nJonas Knutsson har i årtier vært, og er fortsatt, en sentral og trendsettende musiker innen svensk jazz og folkemusikk. Vi i Brønnøysund har vært så heldige å få samarbeidet med han i over 20 år. \nPå denne konserten skal det spilles musikk av Jonas Knutsson og av OBROYs gitarist Ole Bjørn Nygård Berg. Med Jonas sine røtter i jazz og folkemusikk og Ole Bjørns røtter i rocken blir dette en spennende blanding med variert musikk. \n\nJonas Knutsson - saksofoner\nOle Bjørn Nygård Berg - gitarer\nRoy Bjørnli - slagverk\nSanna Frøshaug - fløyte\nEllen Gullhaug - trompet\nHans Kristian Edvardsen - tuba\n\nFORSAMLINGSLOKALET - Brønnøysund\nlørdag 11. april kl. 19.00\nBilletter: kr. 250,-",
      "category": "musikk",
      "dateTime": "2026-04-11T17:00:00.000Z",
      "location": "FORSAMLINGSLOKALET - Brønnøysund",
      "url": "https://www.facebook.com/events/1214003247388441/",
      "collectedAt": "2026-03-07T09:11:41.003Z"
    },
    {
      "title": "Barseltreff på bibliotek",
      "description": "Barseltreff på bibliotek",
      "category": "barn-og-ungdom",
      "dateTime": "2026-04-14T11:00:00",
      "location": "Brønnøy bibliotek",
      "url": "https://bronnoybibliotek.no/arrangementer#/",
      "collectedAt": "2026-03-07T09:58:47.703Z",
      "id": "Brønnøy-bibliotek-2026-04-14T09:00:00.000Z"
    },
    {
      "title": "Trille-Tralle-Treff (babysang)",
      "description": "Onsdag 15.04 kl.11.00 Trille-Tralle-Treff (babysang) Barn og unge - Kefas",
      "category": "barn-og-ungdom",
      "dateTime": "2026-04-15T11:00:00",
      "location": "Brønnøy kirke",
      "url": "https://www.bronnoy.kirken.no/Kalender",
      "collectedAt": "2026-03-07T09:59:29.442Z",
      "id": "Brønnøy-kirke-2026-04-15T09:00:00.000Z"
    },
    {
      "title": "Trille-Tralle-Treff (babysang)",
      "description": "Onsdag 22.04 kl.11.00 Trille-Tralle-Treff (babysang) Barn og unge - Kefas",
      "category": "barn-og-ungdom",
      "dateTime": "2026-04-22T11:00:00",
      "location": "Brønnøy kirke",
      "url": "https://www.bronnoy.kirken.no/Kalender",
      "collectedAt": "2026-03-07T09:59:29.442Z",
      "id": "Brønnøy-kirke-2026-04-22T09:00:00.000Z"
    },
    {
      "id": "1989127691666557",
      "title": "Brønnøysund- Kveli Rånes Bremseth SHOW - Trøndelag du STORE tid",
      "description": "Trøndelag du STORE tid – Festen fortsetter også i 2026!\n\n«Trøndelag du STORE tid» er showet som legger den trønderske beskjedenheten til side og presenterer alt vi trøndere har å være stolte av helt siden steinalderen og fram til nå. Egenskrevet musikk og tekst veves sammen med trønderske allsangfavoritter som får stemningen helt i taket.\n\nDet startet som et VM-vorspiel og fylte åtte saler i Olavshallen i februar 2025. Avisanmelderne var samstemt begeistret. Trønder-Avisa ga showet 20 i stil og Adressa delte ut den første gullmedaljen i ski-VM til showet. De ga samtidig oppfordringen om at dette måtte lanseres som et godt nachspiel.\nVi tok oppfordringen på strak arm, og publikum strømmet til. Morsomme nachspiel har som kjent en tendens til å vare lenger enn opprinnelig planlagt. Etter 27 forestillinger i hjemfylket høsten 2025, har nærmere 10 000 personer kvittert med latterbyger, allsang og taktfast applaus.\n\nFesten fortsetter nå også i 2026!\nShowet rulles nå ut både i og utenfor Trøndelags grenser.\nFlere steder på høstturneen ble utsolgt, så det blir også en del ekstraforestillinger.\n\nHøsten 2025 ble Harald Morten Bremseth lagt inn på sykehus og det var en stund usikkert om vi kunne fullføre turneen.\nVi fikk i fellesskap justert på forestillingen og fant vikarer i egne rekker (les: kostymelager) og dermed slapp vi å avlyse. Bremseth bidro alikevel sterkt på skjerm i forestilingen.\nFram til Harald Morten er friskmeldt vil alle forestillinger spilles som planlagt med Kveli & Rånes på scenen og Bremseth på skjerm.\n\nForestillingen varer i ca 85 min.\n",
      "category": "kunst-og-kultur",
      "dateTime": "2026-04-24T16:30:00.000Z",
      "location": "Brønnøysund samfunnshus",
      "url": "https://www.facebook.com/events/1989127691666557/",
      "collectedAt": "2026-03-07T09:11:41.292Z"
    },
    {
      "id": "1442826520606132",
      "title": "Dr. Bergland - på liv og død",
      "description": "Ventetiden er over, Dr. Bergland er endelig klar med ny forestilling!\n\nI løpet av de siste årene har Jonas Kinge Bergland etablert seg som en av landets største og mest populære komikere. Siden brakdebuten \"Dr. Bergland og den alternative medisin\" i 2016 har han levert intelligent, kompromissløs og etter eget utsagn \"helt brukbar\" standup, for et stadig større publikum og begeistrede anmeldere. Hans andre og tredje forestilling, \"Dr. Bergland bryter taushetsplikten\" og \"Dr. Bergland uten grenser\" solgte begge nærmere 100.000 billetter og er bl.a. blant Latter i Oslos aller største suksesser noensinne.\n\nForventningene er derfor skyhøye når han nå er klar med \"Dr. Bergland på død og liv\".\nDe siste årene har Jonas jobbet som sykehjemslege og fått god anledning til å reflektere over livet, døden, alderdom og om det er noe høyere mening med alt dette. Sånt kan det bli stor humor av, i hvert fall med Dr. Bergland som avsender.\n\nVi gleder oss stort til å presentere et nytt show med vår favorittlege hos oss!\n\nBilletter finner du på Kred sin side hos Ticketmaster. ",
      "category": "kunst-og-kultur",
      "dateTime": "2026-04-24T17:00:00.000Z",
      "location": "Kred",
      "url": "https://www.facebook.com/events/1442826520606132/",
      "collectedAt": "2026-03-07T09:11:40.107Z"
    },
    {
      "title": "Trille-Tralle-Treff (babysang)",
      "description": "Onsdag 29.04 kl.11.00 Trille-Tralle-Treff (babysang) Barn og unge - Kefas",
      "category": "barn-og-ungdom",
      "dateTime": "2026-04-29T11:00:00",
      "location": "Brønnøy kirke",
      "url": "https://www.bronnoy.kirken.no/Kalender",
      "collectedAt": "2026-03-07T09:59:29.442Z",
      "id": "Brønnøy-kirke-2026-04-29T09:00:00.000Z"
    },
    {
      "title": "Gudstjeneste",
      "description": "Torsdag 30.04 kl.11.30 Gudstjeneste Gudstjeneste - Sykehjemmets kapell",
      "category": "tro-og-livssyn",
      "dateTime": "2026-04-30T11:30:00",
      "location": "Brønnøy kirke",
      "url": "https://www.bronnoy.kirken.no/Kalender",
      "collectedAt": "2026-03-07T09:59:29.442Z",
      "id": "Brønnøy-kirke-2026-04-30T09:30:00.000Z"
    },
    {
      "title": "Trille-Tralle-Treff (babysang)",
      "description": "Onsdag 06.05 kl.11.00 Trille-Tralle-Treff (babysang) Barn og unge - Kefas",
      "category": "barn-og-ungdom",
      "dateTime": "2026-05-06T11:00:00",
      "location": "Brønnøy kirke",
      "url": "https://www.bronnoy.kirken.no/Kalender",
      "collectedAt": "2026-03-07T09:59:29.442Z",
      "id": "Brønnøy-kirke-2026-05-06T09:00:00.000Z"
    },
    {
      "title": "Trille-Tralle-Treff (babysang)",
      "description": "Onsdag 13.05 kl.11.00 Trille-Tralle-Treff (babysang) Barn og unge - Kefas",
      "category": "barn-og-ungdom",
      "dateTime": "2026-05-13T11:00:00",
      "location": "Brønnøy kirke",
      "url": "https://www.bronnoy.kirken.no/Kalender",
      "collectedAt": "2026-03-07T09:59:29.442Z",
      "id": "Brønnøy-kirke-2026-05-13T09:00:00.000Z"
    },
    {
      "id": "1584031199293294",
      "title": "Ole Soo og Nils-Ingar Aadne",
      "description": "To av Norges mest populære og morsomste komikere skal ut på veien for å teste nytt materiale. Når nye vitser skal prøves, kan alt skje – og det eneste som er sikkert, er at det blir morsomt! Enten så ler du med dem eller av dem!\n\nNils-Ingar Aadne startet med stand-up i 2003 og har lenge vært en av landets mest profilerte komikere. Han har gjort utallige opptredener og turnert med soloforestillingene EGO og Da var det oss. Han vant Komiprisen for årets gjennombrudd i 2011, har vært sidekick i Senkveld og deltatt i en rekke TV-programmer som Nytt på Nytt, Brille og 71 grader nord. På scenen byr han på personlige observasjoner og skarp samfunnssatire.\n\nOle Soo startet med standup i 2010 og ble raskt omtalt som en kommende stjerne. Han vant P4s «Komidol» samme år og har siden blitt en ettertraktet komiker, tekstforfatter og regissør. Han er også kjent fra podkasten Enkel Servering, som Roastmaster i Rikets Roast på vgtv og Bordtenniskammeratene med blant andre Morten Ramm. Han har også sitt eget talkshow, «Komiker med Ole Soo», der han gir publikum tilgang bak kulissene i komikerverden. Med sin rappkjeftede og energiske stil leverer Ole alltid topp stemning – og latteren sitter alltid løst.\n\nBilletter i salg på Ticketmaster.",
      "category": "kunst-og-kultur",
      "dateTime": "2026-05-15T17:00:00.000Z",
      "location": "Kred",
      "url": "https://www.facebook.com/events/1584031199293294/",
      "collectedAt": "2026-03-07T09:11:45.025Z"
    },
    {
      "title": "Trille-Tralle-Treff (babysang)",
      "description": "Onsdag 20.05 kl.11.00 Trille-Tralle-Treff (babysang) Barn og unge - Kefas",
      "category": "barn-og-ungdom",
      "dateTime": "2026-05-20T11:00:00",
      "location": "Brønnøy kirke",
      "url": "https://www.bronnoy.kirken.no/Kalender",
      "collectedAt": "2026-03-07T09:59:29.442Z",
      "id": "Brønnøy-kirke-2026-05-20T09:00:00.000Z"
    },
    {
      "title": "Trille-Tralle-Treff (babysang)",
      "description": "Onsdag 27.05 kl.11.00 Trille-Tralle-Treff (babysang) Barn og unge - Kefas",
      "category": "barn-og-ungdom",
      "dateTime": "2026-05-27T11:00:00",
      "location": "Brønnøy kirke",
      "url": "https://www.bronnoy.kirken.no/Kalender",
      "collectedAt": "2026-03-07T09:59:29.442Z",
      "id": "Brønnøy-kirke-2026-05-27T09:00:00.000Z"
    },
    {
      "title": "Gudstjeneste",
      "description": "Torsdag 28.05 kl.11.30 Gudstjeneste Gudstjeneste - Sykehjemmets kapell",
      "category": "tro-og-livssyn",
      "dateTime": "2026-05-28T11:30:00",
      "location": "Brønnøy kirke",
      "url": "https://www.bronnoy.kirken.no/Kalender",
      "collectedAt": "2026-03-07T09:59:29.442Z",
      "id": "Brønnøy-kirke-2026-05-28T09:30:00.000Z"
    },
    {
      "title": "Trille-Tralle-Treff (babysang)",
      "description": "Onsdag 03.06 kl.11.00 Trille-Tralle-Treff (babysang) Barn og unge - Kefas",
      "category": "barn-og-ungdom",
      "dateTime": "2026-06-03T11:00:00",
      "location": "Brønnøy kirke",
      "url": "https://www.bronnoy.kirken.no/Kalender",
      "collectedAt": "2026-03-07T09:59:29.442Z",
      "id": "Brønnøy-kirke-2026-06-03T09:00:00.000Z"
    },
    {
      "title": "Lørdagskafé",
      "description": "Lørdag 06.06 kl.12.00 Lørdagskafé Kefas",
      "category": "mat-og-drikke",
      "dateTime": "2026-06-06T12:00:00",
      "location": "Brønnøy kirke",
      "url": "https://www.bronnoy.kirken.no/Kalender",
      "collectedAt": "2026-03-07T09:59:29.442Z",
      "id": "Brønnøy-kirke-2026-06-06T10:00:00.000Z"
    },
    {
      "title": "Trille-Tralle-Treff (babysang)",
      "description": "Onsdag 10.06 kl.11.00 Trille-Tralle-Treff (babysang) Barn og unge - Kefas",
      "category": "barn-og-ungdom",
      "dateTime": "2026-06-10T11:00:00",
      "location": "Brønnøy kirke",
      "url": "https://www.bronnoy.kirken.no/Kalender",
      "collectedAt": "2026-03-07T09:59:29.442Z",
      "id": "Brønnøy-kirke-2026-06-10T09:00:00.000Z"
    },
    {
      "title": "Trille-Tralle-Treff (babysang)",
      "description": "Onsdag 17.06 kl.11.00 Trille-Tralle-Treff (babysang) Barn og unge - Kefas",
      "category": "barn-og-ungdom",
      "dateTime": "2026-06-17T11:00:00",
      "location": "Brønnøy kirke",
      "url": "https://www.bronnoy.kirken.no/Kalender",
      "collectedAt": "2026-03-07T09:59:29.442Z",
      "id": "Brønnøy-kirke-2026-06-17T09:00:00.000Z"
    },
    {
      "id": "1355561149693604",
      "title": "Korfestivalen 2026",
      "description": "Festivalen for glade sangere fra hele landet !\n\nVi håper du tar Torghattfestivalen for kor i Brønnøysund med i betraktningen når du planlegger aktiviteten for ditt kor i 2026. Når vi inviterer til trivelige dager i Nord-Norges sommerby Brønnøysund er du personlig og ditt kor spesielt invitert. \n\nKorfestivalen i Brønnøysund er basert på at sangerne blir satt i sentrum og vi garanterer at sangerne vil sette sitt preg på byen i gater, konsertlokaler, butikker og utesteder under hele festivalen. For å bevare intimitet og muligheten til å bli bedre kjent med andre sangere har vi satt antall deltakere til maksimalt 500 sangere. Selv om sangen står i sentrum vil i like stor grad opplevelsen av kystmiljø og tradisjon være viktige element, sammen med det uformelle under festivalen.\n\nKulinariske opplevelser som; Havets festbord på fredag kveld i pitoreske Tørrfeskbrygga og den stilfulle Festivalbanketten på Samfunnshuset lørdag er høydepunkter.\nKonserten i Torghatthullet må oppleves - en fornemmelse av høytid med naturen som katedral.\n\nKorkonkurransen  er en viktig del av den musikalske utfordringen på festivalen og vi oppfordrer alle kor til å delta på den. Konkurransen vil tradisjonen tro bestå av en profan og en sakral del. Første del foregår fredag ettermiddag like etter åpningsseremonien. Andre del foregår lørdag ettermiddag i Brønnøy kirke. Konserten i kirken vil være en obligatorisk sang for hver klasse (mannskor, damekor og blandakor) som velges ut av dommerne. Hvilke sanger dette blir vil bli annonsert i november 2025\n\nOg - det blir selvsagt premiering i samtlige klasser (dame-, manns- og blandakor)\n\nPå fredag formiddag kan dere få anledning til å glede byens hardtarbeidende befolkning med vakker korsang i lunsjen. På lørdag lager vi show i sentrum med \"Kor for folk\". Det blir også \"Kulturkafè\" på Samfunnshuset der det i tillegg til korsang blir anledning til å bidra med andre kunsteriske innslag.",
      "category": "musikk",
      "dateTime": "2026-06-18T20:00:00.000Z",
      "location": "Brønnøysund By",
      "url": "https://www.facebook.com/events/1355561149693604/",
      "collectedAt": "2026-03-07T09:11:45.563Z"
    },
    {
      "title": "Gudstjeneste",
      "description": "Torsdag 25.06 kl.11.30 Gudstjeneste Gudstjeneste - Sykehjemmets kapell",
      "category": "tro-og-livssyn",
      "dateTime": "2026-06-25T11:30:00",
      "location": "Brønnøy kirke",
      "url": "https://www.bronnoy.kirken.no/Kalender",
      "collectedAt": "2026-03-07T09:59:29.442Z",
      "id": "Brønnøy-kirke-2026-06-25T09:30:00.000Z"
    },
    {
      "id": "1518436712711995",
      "title": "Rootsfestivalen 2026",
      "description": "Helgelands største kulturarrangement\n4 dager med konserter, utstillinger og aktiviteter for store og små i Brønnøysund sentrum. Gratis program hele onsdag og på dagtid torsdag, fredag og lørdag. Kveldskonserter på utescene torsdag, fredag, lørdag. Lokale, regionale, nasjonale og internasjonale artister.\nKonsertstart : 18:30 Dørene åpner : 17:30\nServering : Mat Øl / Vin\nAldersgrense : 18 år på kveld",
      "category": "musikk",
      "dateTime": "2026-07-15T11:00:00.000Z",
      "location": "Brønnøysund Sentrum",
      "url": "https://www.facebook.com/events/1518436712711995/",
      "collectedAt": "2026-03-07T09:11:39.768Z"
    },
    {
      "title": "Gudstjeneste",
      "description": "Torsdag 30.07 kl.11.30 Gudstjeneste Gudstjeneste - Sykehjemmets kapell",
      "category": "tro-og-livssyn",
      "dateTime": "2026-07-30T11:30:00",
      "location": "Brønnøy kirke",
      "url": "https://www.bronnoy.kirken.no/Kalender",
      "collectedAt": "2026-03-07T09:59:29.442Z",
      "id": "Brønnøy-kirke-2026-07-30T09:30:00.000Z"
    },
    {
      "title": "Gudstjeneste",
      "description": "Torsdag 27.08 kl.11.30 Gudstjeneste Gudstjeneste - Sykehjemmets kapell",
      "category": "tro-og-livssyn",
      "dateTime": "2026-08-27T11:30:00",
      "location": "Brønnøy kirke",
      "url": "https://www.bronnoy.kirken.no/Kalender",
      "collectedAt": "2026-03-07T09:59:29.442Z",
      "id": "Brønnøy-kirke-2026-08-27T09:30:00.000Z"
    },
    {
      "title": "Gudstjeneste",
      "description": "Torsdag 24.09 kl.11.30 Gudstjeneste Gudstjeneste - Sykehjemmets kapell",
      "category": "tro-og-livssyn",
      "dateTime": "2026-09-24T11:30:00",
      "location": "Brønnøy kirke",
      "url": "https://www.bronnoy.kirken.no/Kalender",
      "collectedAt": "2026-03-07T09:59:29.442Z",
      "id": "Brønnøy-kirke-2026-09-24T09:30:00.000Z"
    },
    {
      "title": "Espen Abrahamsen - Avantgarde",
      "description": "Espen Abrahamsen er endelig klar med sitt første helaftens standupshow. Du kjenner ham fra TV og podkaster, men det er på scenen Espen virkelig briljerer. Siden debuten på standupscenen i 2020 har målet vært klart, et eget show og en Norgesturné.",
      "category": "kunst-og-kultur",
      "dateTime": "2026-10-10T19:00:00",
      "location": "Kred",
      "url": "https://www.cafekred.no/arrangementer",
      "collectedAt": "2026-03-07T09:58:24.097Z",
      "id": "Kred-2026-10-10T17:00:00.000Z"
    },
    {
      "title": "Gudstjeneste",
      "description": "Torsdag 29.10 kl.11.30 Gudstjeneste Gudstjeneste - Sykehjemmets kapell",
      "category": "tro-og-livssyn",
      "dateTime": "2026-10-29T11:30:00",
      "location": "Brønnøy kirke",
      "url": "https://www.bronnoy.kirken.no/Kalender",
      "collectedAt": "2026-03-07T09:59:29.442Z",
      "id": "Brønnøy-kirke-2026-10-29T10:30:00.000Z"
    },
    {
      "title": "Gudstjeneste",
      "description": "Torsdag 26.11 kl.11.30 Gudstjeneste Gudstjeneste - Sykehjemmets kapell",
      "category": "tro-og-livssyn",
      "dateTime": "2026-11-26T11:30:00",
      "location": "Brønnøy kirke",
      "url": "https://www.bronnoy.kirken.no/Kalender",
      "collectedAt": "2026-03-07T09:59:29.442Z",
      "id": "Brønnøy-kirke-2026-11-26T10:30:00.000Z"
    },
    {
      "title": "Gudstjeneste",
      "description": "Torsdag 31.12 kl.11.30 Gudstjeneste Gudstjeneste - Sykehjemmets kapell",
      "category": "tro-og-livssyn",
      "dateTime": "2026-12-31T11:30:00",
      "location": "Brønnøy kirke",
      "url": "https://www.bronnoy.kirken.no/Kalender",
      "collectedAt": "2026-03-07T09:59:29.442Z",
      "id": "Brønnøy-kirke-2026-12-31T10:30:00.000Z"
    }
  ]
}